<?xml version="1.0" ?><jasbro.game.items.Equipment><value>250000</value><name>Spermivore Parasite</name><description>About the size of a smoking pipe, this parasite resides in the womb of 
it's host, feeding on sperm and ovum thus eliminating any chance of 
pregnancy. It also secretes aphrodisiac fluid, making it's host horny
and ready for love making so it'll get more sperm.</description><type>EQUIPMENT</type><spawnData><jasbro.game.items.ItemSpawnData><itemLocation>TRAVELLINGMERCHANT</itemLocation><chance>10</chance><minAmount>1</minAmount><maxAmount>1</maxAmount></jasbro.game.items.ItemSpawnData><jasbro.game.items.ItemSpawnData><itemLocation>BLACKMARKET</itemLocation><chance>1</chance><minAmount>1</minAmount><maxAmount>1</maxAmount></jasbro.game.items.ItemSpawnData></spawnData><imageSelection><image>SEN_PARASITE_VAGINA.png</image><imageLocation>LOCAL</imageLocation><background>false</background><target>character</target></imageSelection><equipmentEffects><jasbro.game.items.equipmentEffect.EquipmentTraitRequirement><trait>WILD</trait></jasbro.game.items.equipmentEffect.EquipmentTraitRequirement><jasbro.game.items.equipmentEffect.EquipmentChangeCalculatedAttributeFixed><attributeType>PREGNANCYCHANCE</attributeType><amount>-1000.0</amount></jasbro.game.items.equipmentEffect.EquipmentChangeCalculatedAttributeFixed><jasbro.game.items.equipmentEffect.EquipmentChangeAttribute><attributeType class="jasbro.game.character.specialization.SpecializationAttribute">SEDUCTION</attributeType><amount>20</amount></jasbro.game.items.equipmentEffect.EquipmentChangeAttribute><jasbro.game.items.equipmentEffect.EquipmentChangeAttributeGain><attributeType class="jasbro.game.character.attributes.Sextype">VAGINAL</attributeType><amountPercent>-10</amountPercent></jasbro.game.items.equipmentEffect.EquipmentChangeAttributeGain><jasbro.game.items.equipmentEffect.EquipmentDailyAttributeChange><attributeType class="jasbro.game.character.attributes.Sextype">MONSTER</attributeType><amount>1</amount></jasbro.game.items.equipmentEffect.EquipmentDailyAttributeChange><jasbro.game.items.equipmentEffect.EquipmentAddTrait><trait>NYMPHO</trait></jasbro.game.items.equipmentEffect.EquipmentAddTrait><jasbro.game.items.equipmentEffect.EquipmentChangeCalculatedAttributeFixed><attributeType>AMOUNTCUSTOMERSPERSHIFT</attributeType><amount>1.0</amount></jasbro.game.items.equipmentEffect.EquipmentChangeCalculatedAttributeFixed></equipmentEffects><equipmentType>ACCESSORY</equipmentType></jasbro.game.items.Equipment>