<?xml version="1.0" ?><jasbro.game.items.Equipment><value>80000</value><name>Shield of Love</name><description>The inner side of this heart-shaped great shield is padded with
quilted mattress. When flipped over, this shield could be placed
on the ground and used as bed or couch. This type of shield is
commonly carried by pilgrims of the Sisterhood, providing their
customer with a comfortable place for pleasure anywhere on
their Pilgrimage of Prostitution.</description><type>EQUIPMENT</type><spawnData><jasbro.game.items.ItemSpawnData><itemLocation>TRAVELLINGMERCHANT</itemLocation><chance>10</chance><minAmount>1</minAmount><maxAmount>1</maxAmount></jasbro.game.items.ItemSpawnData><jasbro.game.items.ItemSpawnData><itemLocation>BLACKMARKET</itemLocation><chance>1</chance><minAmount>1</minAmount><maxAmount>1</maxAmount></jasbro.game.items.ItemSpawnData></spawnData><imageSelection><image>SEN_SHIELD_LOVE.png</image><imageLocation>LOCAL</imageLocation><background>false</background><target>character</target></imageSelection><equipmentEffects><jasbro.game.items.equipmentEffect.EquipmentAttributeRequirement><attributeType class="jasbro.game.character.attributes.BaseAttributeTypes">STRENGTH</attributeType><amount>20</amount></jasbro.game.items.equipmentEffect.EquipmentAttributeRequirement><jasbro.game.items.equipmentEffect.EquipmentChangeArmor><amount>300</amount></jasbro.game.items.equipmentEffect.EquipmentChangeArmor><jasbro.game.items.equipmentEffect.EquipmentChangeCalculatedAttributeFixed><attributeType>BLOCKCHANCE</attributeType><amount>10.0</amount></jasbro.game.items.equipmentEffect.EquipmentChangeCalculatedAttributeFixed><jasbro.game.items.equipmentEffect.EquipmentChangeCalculatedAttributeFixed><attributeType>BLOCKAMOUNT</attributeType><amount>10.0</amount></jasbro.game.items.equipmentEffect.EquipmentChangeCalculatedAttributeFixed><jasbro.game.items.equipmentEffect.EquipmentChangeCustomerTypeSatisfaction><customerType>BUM</customerType><amount>10</amount></jasbro.game.items.equipmentEffect.EquipmentChangeCustomerTypeSatisfaction><jasbro.game.items.equipmentEffect.EquipmentChangeCustomerTypeSatisfaction><customerType>PEASANT</customerType><amount>8</amount></jasbro.game.items.equipmentEffect.EquipmentChangeCustomerTypeSatisfaction><jasbro.game.items.equipmentEffect.EquipmentChangeCustomerTypeSatisfaction><customerType>SOLDIER</customerType><amount>5</amount></jasbro.game.items.equipmentEffect.EquipmentChangeCustomerTypeSatisfaction><jasbro.game.items.equipmentEffect.EquipmentChangeCustomerTypeSatisfaction><customerType>MERCHANT</customerType><amount>5</amount></jasbro.game.items.equipmentEffect.EquipmentChangeCustomerTypeSatisfaction></equipmentEffects><equipmentType>ACCESSORY</equipmentType><accessoryType>ONEHANDED</accessoryType></jasbro.game.items.Equipment>